Metadata-Version: 2.1
Name: python-video
Version: 0.0.0
Summary: A lightweight module for simple handling of video frames and audio.
Home-page: https://github.com/Shahaf-F-S/project-template
Author: Shahaf Frank-Shapir
Author-email: shahaffrs@gmail.com
License: MIT
Classifier: Intended Audience :: Developers
Classifier: License :: OSI Approved :: MIT License
Classifier: Programming Language :: Python
Classifier: Programming Language :: Python :: 3
Classifier: Programming Language :: Python :: 3.8
Classifier: Programming Language :: Python :: 3.9
Classifier: Programming Language :: Python :: 3.10
Classifier: Programming Language :: Python :: 3.11
Classifier: Operating System :: OS Independent
Requires-Dist: numpy
Requires-Dist: opencv-python
Requires-Dist: moviepy
Requires-Dist: tqdm
Provides-Extra: dev
Requires-Dist: pdoc3; extra == "dev"
Requires-Dist: twine; extra == "dev"
Requires-Dist: pytest; extra == "dev"
